gnome_keyring_gpg_unlock/GpgSecret.py
gnome_keyring_gpg_unlock/Keyring.py
gnome_keyring_gpg_unlock/__init__.py
gnome_keyring_gpg_unlock/bin/__init__.py
gnome_keyring_gpg_unlock/bin/console.py
gnome_keyring_gpg_unlock/interface/__init__.py
gnome_keyring_gpg_unlock/interface/cli.py
gnome_keyring_gpg_unlock/interface/cli/__init__.py
gnome_keyring_gpg_unlock/interface/cli/abstract.py
gnome_keyring_gpg_unlock/interface/cli/setup.py
gnome_keyring_gpg_unlock/interface/cli/unlock.py
gnome_keyring_gpg_unlock-0.0.2.dist-info/METADATA
gnome_keyring_gpg_unlock-0.0.2.dist-info/WHEEL
gnome_keyring_gpg_unlock-0.0.2.dist-info/entry_points.txt
gnome_keyring_gpg_unlock-0.0.2.dist-info/top_level.txt
gnome_keyring_gpg_unlock-0.0.2.dist-info/RECORD
