Metadata-Version: 2.1
Name: gnome-keyring-gpg-unlock
Version: 0.0.2
Summary: Auto unlock your default gnome-keyring with a gpg encrypted password
Home-page: https://github.com/claudio-walser/gnome-keyring-gpg-unlock
Author: Claudio Walser
Author-email: info@gitcd.io
License: Apache License
Keywords: keyring,gnome-keyring,unlock,gnome-keyring-unlock
Classifier: Development Status :: 5 - Production/Stable
Classifier: Environment :: Console
Classifier: Intended Audience :: Information Technology
Classifier: License :: OSI Approved :: Apache Software License
Classifier: Operating System :: POSIX :: Linux
Classifier: Programming Language :: Python :: 3 :: Only
Classifier: Topic :: Security
Requires-Dist: simpcli
Requires-Dist: python-gnupg
Requires-Dist: argparse
Requires-Dist: argcomplete
Requires-Dist: typing
